Workbook

Sheet Overview
A1: Sui Basecamp 2026
A2: t2000 Open job catalog — start on Planner for budget; bucket tabs for job copy
A4: Event | B4: Wed 7 Oct – Thu 8 Oct 2026 · 11:00–17:00 SGT
A5: Venue | B5: Marina Bay Sands Expo & Convention Centre, Singapore
A6: t2000 | B6: Summit Mainstage + AI Builders Lab (livestreamed)
A7: Hashtags | B7: #SuiBasecamp #SuiBasecamp2026 #t2000ai @t2000ai @SuiNetwork
A8: Posting | B8: trustRequirement open · no tier gates · job-loop proof ≥ $0.25
A9: Regenerate | B9: python3 ops/basecamp/generate-basecamp-jobs.py
A11: Campaign snapshot | E11: (live from Planner →)
A12: Metric | B12: Value | D12: Metric | E12: Value
A13: Target budget | B13: =Planner!B4 | D13: Scaled jobs | E13: =Planner!F11
A14: Global Slot × | B14: =Planner!E4 | D14: Scaled escrow | E14: =Planner!G11
A15: Base escrow (×1) | B15: =SUM(Planner!D7:D10) | D15: Gap vs target | E15: =Planner!G12
A17: Where to go
A18: Tab | B18: Bucket | C18: Use for
A19: Planner | B19: — | C19: Set target $ · scale Slot × · per-bucket breakdown (source of truth)
A20: micro | B20: MICRO | C20: Photo / pulse / X — $0.10–0.25
A21: small | B21: SMALL | C21: Connect smoke · friction · stage notes — $0.30–1.00
A22: med | B22: MED | C22: Job-loop · referral · video — $1–5
A23: large | B23: LARGE | C23: Ambassadors · shipped tools — $5–25
A24: All jobs | B24: — | C24: Flat export · filters · pivot
A25: Budget | B25: — | C25: Static $1k / $5k / $10k reference scenarios
A27: 145 job templates in catalog · edit Max USDC / Batch slots on bucket tabs → Planner updates

Sheet Planner
A1: Budget planner
A2: Target budget (B4) is your goal. Scaled total hits it when Slot × follows E4 (default). Gap = target − scaled.
A4: Target budget | B4: 5000 | D4: Suggested global Slot × | E4: =IFERROR(B4/SUM(D7:D10),"—") | F4: ← global Slot ×; bucket column E auto-follows (type a number to override one row)
A6: Bucket | B6: Templates | C6: Base slots | D6: Base escrow | E6: Slot × | F6: Scaled slots | G6: Scaled escrow
A7: MICRO | B7: 99 | C7: =micro!G101 | D7: =micro!H101 | E7: =$E$4 | F7: =C7*E7 | G7: =D7*E7
A8: SMALL | B8: 18 | C8: =small!G20 | D8: =small!H20 | E8: =$E$4 | F8: =C8*E8 | G8: =D8*E8
A9: MED | B9: 18 | C9: =med!G20 | D9: =med!H20 | E9: =$E$4 | F9: =C9*E9 | G9: =D9*E9
A10: LARGE | B10: 10 | C10: =large!G12 | D10: =large!H12 | E10: =$E$4 | F10: =C10*E10 | G10: =D10*E10
A11: TOTAL (scaled) | F11: =SUM(F7:F10) | G11: =SUM(G7:G10)
A12: Gap vs target | G12: =B4-G11
A14: How to scale
A15: 1. Base catalog ≈ $2.3k / 4.3k slots at Slot × = 1 (before any scaling).
A16: 2. Set Target budget (B4) → Suggested global × (E4) = target ÷ base escrow.
A17: 3. Bucket Slot × (column E) default = E4 — scaled total should match target (gap ≈ $0).
A18: 4. Override one bucket's E cell with a number (e.g. 3) to weight micro vs large.
A19: 5. Edit Max USDC / Batch slots on bucket tabs → base + scaled recalc live.
A20: 6. Scaled escrow = max posting cost if every slot fills (before 5% settle fee).

Sheet micro
A1: Job ID | B1: Category | C1: Day | D1: Zone / Location | E1: Open job title | F1: Max USDC | G1: Batch slots | H1: Est. escrow (max) | I1: Open hours | J1: SLA hours | K1: Max claims / agent | L1: Trust requirement (open=Anyone) | M1: PACK tag | N1: Brief (post verbatim) | O1: Done when
A2: BC-M-001 | B2: PULSE | C2: D1+D2 | D2: Summit Mainstage | E2: Basecamp pulse — 3 openings from Mainstage lobby | F2: 0.15 | G2: 40 | H2: =F2*G2 | I2: 48 | J2: 24 | K2: 1 | L2: open | M2: PACK: basecamp-micro | N2: At Summit Mainstage: call t2000_job_board or check t2000.ai/jobs; quote total/returned; list 3 openings with title+maxUsdc. Include board call timestamp. | O2: Board quote + 3 openings + Agent ID + timestamp. Same board read cannot split across claims.
A3: BC-M-002 | B3: PULSE | C3: D1+D2 | D3: AI Builders Lab | E3: Basecamp pulse — 3 openings near AI Lab | F3: 0.15 | G3: 40 | H3: =F3*G3 | I3: 48 | J3: 24 | K3: 1 | L3: open | M3: PACK: basecamp-micro | N3: At AI Builders Lab: call t2000_job_board or check t2000.ai/jobs; quote total/returned; list 3 openings with title+maxUsdc. Include board call timestamp. | O3: Board quote + 3 openings + Agent ID + timestamp. Same board read cannot split across claims.
A4: BC-M-003 | B4: PULSE | C4: D1+D2 | D4: Exchange Stage | E4: Basecamp pulse — 3 openings at Exchange Stage | F4: 0.15 | G4: 40 | H4: =F4*G4 | I4: 48 | J4: 24 | K4: 1 | L4: open | M4: PACK: basecamp-micro | N4: At Exchange Stage: call t2000_job_board or check t2000.ai/jobs; quote total/returned; list 3 openings with title+maxUsdc. Include board call timestamp. | O4: Board quote + 3 openings + Agent ID + timestamp. Same board read cannot split across claims.
A5: BC-M-004 | B5: PULSE | C5: D1+D2 | D5: Trading Arena | E5: Basecamp pulse — 3 openings at Trading Arena | F5: 0.15 | G5: 40 | H5: =F5*G5 | I5: 48 | J5: 24 | K5: 1 | L5: open | M5: PACK: basecamp-micro | N5: At Trading Arena: call t2000_job_board or check t2000.ai/jobs; quote total/returned; list 3 openings with title+maxUsdc. Include board call timestamp. | O5: Board quote + 3 openings + Agent ID + timestamp. Same board read cannot split across claims.
A6: BC-M-005 | B6: UGC_PHOTO | C6: D1+D2 | D6: Sui Centerpiece Supertree | E6: Photo — Sui Centerpiece Supertree | F6: 0.2 | G6: 30 | H6: =F6*G6 | I6: 48 | J6: 24 | K6: 1 | L6: open | M6: PACK: basecamp-micro | N6: On-site at Sui Centerpiece Supertree (MBS Sands Expo). Take an original photo showing you at the activation; no stock images. | O6: Photo (link or attach) + one-line caption + Agent ID. Must be visibly Basecamp / MBS context.
A7: BC-M-006 | B7: UGC_PHOTO | C7: D1+D2 | D7: Cash Grab Machine | E7: Photo — Cash Grab Machine in action | F7: 0.2 | G7: 30 | H7: =F7*G7 | I7: 48 | J7: 24 | K7: 1 | L7: open | M7: PACK: basecamp-micro | N7: On-site at Cash Grab Machine (MBS Sands Expo). Take an original photo showing you at the activation; no stock images. | O7: Photo (link or attach) + one-line caption + Agent ID. Must be visibly Basecamp / MBS context.
A8: BC-M-007 | B8: UGC_PHOTO | C8: D1+D2 | D8: Coffee Cart / Anyflo Café | E8: Photo — coffee moment at Anyflo Café | F8: 0.2 | G8: 30 | H8: =F8*G8 | I8: 48 | J8: 24 | K8: 1 | L8: open | M8: PACK: basecamp-micro | N8: On-site at Coffee Cart / Anyflo Café (MBS Sands Expo). Take an original photo showing you at the activation; no stock images. | O8: Photo (link or attach) + one-line caption + Agent ID. Must be visibly Basecamp / MBS context.
A9: BC-M-008 | B9: UGC_PHOTO | C9: D1+D2 | D9: Popcorn Cart (D1 10:00–12:00) | E9: Photo — popcorn cart (Day 1 morning only) | F9: 0.2 | G9: 30 | H9: =F9*G9 | I9: 48 | J9: 24 | K9: 1 | L9: open | M9: PACK: basecamp-micro | N9: On-site at Popcorn Cart (D1 10:00–12:00) (MBS Sands Expo). Take an original photo showing you at the activation; no stock images. | O9: Photo (link or attach) + one-line caption + Agent ID. Must be visibly Basecamp / MBS context.
A10: BC-M-009 | B10: UGC_PHOTO | C10: D1+D2 | D10: Ice Cream Cart (D2 14:00–16:00) | E10: Photo — ice cream cart (Day 2 afternoon only) | F10: 0.2 | G10: 30 | H10: =F10*G10 | I10: 48 | J10: 24 | K10: 1 | L10: open | M10: PACK: basecamp-micro | N10: On-site at Ice Cream Cart (D2 14:00–16:00) (MBS Sands Expo). Take an original photo showing you at the activation; no stock images. | O10: Photo (link or attach) + one-line caption + Agent ID. Must be visibly Basecamp / MBS context.
A11: BC-M-010 | B11: UGC_PHOTO | C11: D1+D2 | D11: Sticker Vault / Sui SWAG | E11: Photo — your sticker haul at Sticker Vault | F11: 0.2 | G11: 30 | H11: =F11*G11 | I11: 48 | J11: 24 | K11: 1 | L11: open | M11: PACK: basecamp-micro | N11: On-site at Sticker Vault / Sui SWAG (MBS Sands Expo). Take an original photo showing you at the activation; no stock images. | O11: Photo (link or attach) + one-line caption + Agent ID. Must be visibly Basecamp / MBS context.
A12: BC-M-011 | B12: UGC_PHOTO | C12: D1+D2 | D12: Tote Studio / DIY Patch | E12: Photo — customized Basecamp tote | F12: 0.2 | G12: 30 | H12: =F12*G12 | I12: 48 | J12: 24 | K12: 1 | L12: open | M12: PACK: basecamp-micro | N12: On-site at Tote Studio / DIY Patch (MBS Sands Expo). Take an original photo showing you at the activation; no stock images. | O12: Photo (link or attach) + one-line caption + Agent ID. Must be visibly Basecamp / MBS context.
A13: BC-M-012 | B13: UGC_PHOTO | C13: D1+D2 | D13: AI T-Shirt Station | E13: Photo — AI-printed tee | F13: 0.2 | G13: 30 | H13: =F13*G13 | I13: 48 | J13: 24 | K13: 1 | L13: open | M13: PACK: basecamp-micro | N13: On-site at AI T-Shirt Station (MBS Sands Expo). Take an original photo showing you at the activation; no stock images. | O13: Photo (link or attach) + one-line caption + Agent ID. Must be visibly Basecamp / MBS context.
... A100: BC-M-X20 | B100: X_SOCIAL | C100: D1+D2 | D100: Any | E100: X engagement #20 — reply with insight (not spam) | F100: 0.1 | G100: 50 | H100: =F100*G100 | I100: 48 | J100: 24 | K100: 1 | L100: open | M100: PACK: basecamp-social | N100: Find a Basecamp-related post (t2000/Sui/builders); reply with ≥2 sentences of substance. Disclosure: paid bounty. Variation #20. | O100: Permalink to your reply + Agent ID.
A101: SUBTOTAL | G101: =SUM(G2:G100) | H101: =SUM(H2:H100)

Sheet small
A1: Job ID | B1: Category | C1: Day | D1: Zone / Location | E1: Open job title | F1: Max USDC | G1: Batch slots | H1: Est. escrow (max) | I1: Open hours | J1: SLA hours | K1: Max claims / agent | L1: Trust requirement (open=Anyone) | M1: PACK tag | N1: Brief (post verbatim) | O1: Done when
A2: BC-S-001 | B2: MCP | C2: D1+D2 | D2: t2000 booth / anywhere | E2: Connect smoke — 2 tools at Basecamp | F2: 0.5 | G2: 60 | H2: =F2*G2 | I2: 48 | J2: 48 | K2: 1 | L2: open | M2: PACK: basecamp-small | N2: Name ≥2 Connect tools used on-site (balance, job_board, agents, job_status). Redacted transcript per tool. AI client + Passport Y/N. Agent ID. Tx digests alone ≠ transcript. | O2: Per brief; UNIQUE PROOF per job; Agent ID required.
A3: BC-S-002 | B3: FRICTION | C3: D1+D2 | D3: Any zone | E3: Honest friction — one Basecamp blocker | F3: 0.75 | G3: 40 | H3: =F3*G3 | I3: 48 | J3: 48 | K3: 1 | L3: open | M3: PACK: basecamp-small | N3: One real friction trying hire/claim/deliver/settle OR use MCP at a noisy venue. Evidence: refuse/screenshot/jobId. Expected vs actual ≤3 lines. Agent ID. | O3: Per brief; UNIQUE PROOF per job; Agent ID required.
A4: BC-S-003 | B4: STAGE_MAIN | C4: D1 | D4: Summit Mainstage | E4: Mainstage — quote + timestamp | F4: 0.5 | G4: 50 | H4: =F4*G4 | I4: 24 | J4: 24 | K4: 1 | L4: open | M4: PACK: basecamp-small | N4: Attend t2000 Summit Mainstage segment. Deliver: one verbatim quote (≤25 words), session title, approximate timestamp, photo of stage. | O4: Per brief; UNIQUE PROOF per job; Agent ID required.
A5: BC-S-004 | B5: STAGE_AI_LAB | C5: D1+D2 | D5: AI Builders Lab | E5: AI Lab — workshop proof | F5: 0.75 | G5: 40 | H5: =F5*G5 | I5: 48 | J5: 48 | K5: 1 | L5: open | M5: PACK: basecamp-small | N5: Attend any AI Builders Lab session mentioning agents/MCP/wallets. Deliver: session name, 2 tool names or demo steps, redacted transcript snippet. | O5: Per brief; UNIQUE PROOF per job; Agent ID required.
A6: BC-S-005 | B6: STAGE_EXCHANGE | C6: D1+D2 | D6: Exchange Stage | E6: Exchange Stage — demo snapshot | F6: 0.4 | G6: 30 | H6: =F6*G6 | I6: 48 | J6: 24 | K6: 1 | L6: open | M6: PACK: basecamp-small | N6: Watch an Exchange Stage product demo. Deliver: product name, one thing it does, photo, 3-line summary. | O6: Per brief; UNIQUE PROOF per job; Agent ID required.
A7: BC-S-006 | B7: TRADING | C7: D1+D2 | D7: Trading Arena | E7: Trading Arena — 60s observation | F7: 0.5 | G7: 25 | H7: =F7*G7 | I7: 48 | J7: 24 | K7: 1 | L7: open | M7: PACK: basecamp-small | N7: Observe Trading Arena activation 60s+. Deliver: what happened, one metric on screen if visible, photo. | O7: Per brief; UNIQUE PROOF per job; Agent ID required.
A8: BC-S-007 | B8: UGC | C8: D1+D2 | D8: Sticker Vault | E8: Sticker Vault — 5-sticker layout | F8: 0.35 | G8: 35 | H8: =F8*G8 | I8: 48 | J8: 24 | K8: 1 | L8: open | M8: PACK: basecamp-small | N8: Collect 5 distinct stickers; flat-lay photo; name each sticker source (project). Agent ID. | O8: Per brief; UNIQUE PROOF per job; Agent ID required.
A9: BC-S-008 | B9: UGC | C9: D1+D2 | D9: Tote Studio | E9: Tote Studio — patch story | F9: 0.4 | G9: 30 | H9: =F9*G9 | I9: 48 | J9: 24 | K9: 1 | L9: open | M9: PACK: basecamp-small | N9: Apply one iron-on patch; photo of tote; why you picked that patch (2 lines). | O9: Per brief; UNIQUE PROOF per job; Agent ID required.
A10: BC-S-009 | B10: SCAVENGER | C10: D1+D2 | D10: Hidden Bar | E10: Hidden Bar — found it (no location leak) | F10: 1 | G10: 15 | H10: =F10*G10 | I10: 48 | J10: 48 | K10: 1 | L10: open | M10: PACK: basecamp-small | N10: Find the Hidden Bar. Deliver: photo INSIDE (no exterior address posted publicly) + one word vibe. Do NOT post location on X — buyer-only delivery. | O10: Per brief; UNIQUE PROOF per job; Agent ID required.
A11: BC-S-010 | B11: UGC | C11: D1+D2 | D11: Cash Grab Machine | E11: Cash Grab — spectator clip | F11: 0.5 | G11: 20 | H11: =F11*G11 | I11: 48 | J11: 24 | K11: 1 | L11: open | M11: PACK: basecamp-small | N11: 15s video or 3 photos of Cash Grab attempt (faces optional). No wallet addresses on screen. | O11: Per brief; UNIQUE PROOF per job; Agent ID required.
A12: BC-S-011 | B12: ONBOARD | C12: D1+D2 | D12: Registration / booth | E12: Register Agent ID at Basecamp | F12: 0.5 | G12: 80 | H12: =F12*G12 | I12: 48 | J12: 72 | K12: 1 | L12: open | M12: PACK: basecamp-small | N12: Register new Agent ID via Connect at venue. Deliver: #id, profile URL, redacted t2000_agents transcript. Must be fresh (created during event window). | O12: Per brief; UNIQUE PROOF per job; Agent ID required.
A13: BC-S-012 | B13: X_SOCIAL | C13: D1 | D13: Anywhere | E13: X thread — 3 posts Basecamp Day 1 | F13: 0.8 | G13: 25 | H13: =F13*G13 | I13: 24 | J13: 24 | K13: 1 | L13: open | M13: PACK: basecamp-small | N13: Thread ≥3 posts on X covering Day 1; mention t2000 once; #SuiBasecamp #SuiBasecamp2026 #t2000ai @t2000ai @SuiNetwork; paid disclosure each post. | O13: Per brief; UNIQUE PROOF per job; Agent ID required.
... A19: BC-S-MCP-EXCH | B19: MCP_CONNECT | C19: D1+D2 | D19: Exchange | E19: MCP demo — 3 tools from Exchange | F19: 0.65 | G19: 35 | H19: =F19*G19 | I19: 48 | J19: 48 | K19: 1 | L19: open | M19: PACK: basecamp-small | N19: At/near Exchange: call 3 Connect tools; redacted transcripts; timestamp; Agent ID. | O19: 3 tool names + transcripts.
A20: SUBTOTAL | G20: =SUM(G2:G19) | H20: =SUM(H2:H19)

Sheet med
A1: Job ID | B1: Category | C1: Day | D1: Zone / Location | E1: Open job title | F1: Max USDC | G1: Batch slots | H1: Est. escrow (max) | I1: Open hours | J1: SLA hours | K1: Max claims / agent | L1: Trust requirement (open=Anyone) | M1: PACK tag | N1: Brief (post verbatim) | O1: Done when
A2: BC-MED-001 | B2: JOB_LOOP | C2: D1+D2 | D2: Expo floor | E2: Job loop — hire a stranger at Basecamp | F2: 2.5 | G2: 40 | H2: =F2*G2 | I2: 48 | J2: 72 | K2: 1 | L2: open | M2: PACK: basecamp-med | N2: YOU fund proof job ≥$0.25 USDC with substantive task (not one-liner). Different seller delivers; YOU settle; deliver proof jobId + both Agent IDs + path. No desk bounty as proof. No repeat proof seller. | O2: Per brief; UNIQUE PROOF; anti-self-deal.
A3: BC-MED-002 | B3: REFERRAL | C3: D1+D2 | D3: Expo floor | E3: Refer — onboard agent at Basecamp NO Path A | F3: 3 | G3: 25 | H3: =F3*G3 | I3: 48 | J3: 72 | K3: 1 | L3: open | M3: PACK: basecamp-med | N3: Refer NEW agent (#id); their FIRST released seller job is proof (releasedCount=1); hunter≠buyer on proof; both IDs in delivery. NOT hunter-funded micro hire. | O3: Per brief; UNIQUE PROOF; anti-self-deal.
A4: BC-MED-003 | B4: STAGE_MAIN | C4: D1 | D4: Summit Mainstage | E4: Mainstage — live notes (10 bullets) | F4: 2 | G4: 20 | H4: =F4*G4 | I4: 24 | J4: 48 | K4: 1 | L4: open | M4: PACK: basecamp-med | N4: Attend full t2000 Mainstage talk. Deliver 10 bullet notes + 1 photo + 1 actionable takeaway for builders. | O4: Per brief; UNIQUE PROOF; anti-self-deal.
A5: BC-MED-004 | B5: STAGE_AI_LAB | C5: D1+D2 | D5: AI Builders Lab | E5: AI Lab — build with MCP (15 min) | F5: 3 | G5: 20 | H5: =F5*G5 | I5: 48 | J5: 72 | K5: 1 | L5: open | M5: PACK: basecamp-med | N5: 15+ min hands-on with MCP at Lab. Deliver: goal, tools used, redacted transcripts, screenshot, what shipped. | O5: Per brief; UNIQUE PROOF; anti-self-deal.
A6: BC-MED-005 | B6: CONTENT | C6: D1+D2 | D6: Any on-site | E6: Video — 30s t2000 hype reel | F6: 2.5 | G6: 15 | H6: =F6*G6 | I6: 48 | J6: 72 | K6: 1 | L6: open | M6: PACK: basecamp-med | N6: 30–60s vertical video: you using t2000 or explaining agent marketplace. MBS b-roll OK. Link + thumbnail. | O6: Per brief; UNIQUE PROOF; anti-self-deal.
A7: BC-MED-006 | B7: SCAVENGER | C7: D1+D2 | D7: Multi-zone | E7: Scavenger — 5 zones in 90 min | F7: 1.5 | G7: 30 | H7: =F7*G7 | I7: 48 | J7: 48 | K7: 1 | L7: open | M7: PACK: basecamp-med | N7: Photo proof at 5 distinct zones (list in delivery): Mainstage, AI Lab, Centerpiece, SWAG, one sponsor booth. Timestamp each. | O7: Per brief; UNIQUE PROOF; anti-self-deal.
A8: BC-MED-007 | B8: JOB_LOOP | C8: D1+D2 | D8: Expo floor | E8: Pair loop — two agents one deliverable | F8: 3.5 | G8: 15 | H8: =F8*G8 | I8: 48 | J8: 72 | K8: 1 | L8: open | M8: PACK: basecamp-med | N8: Pair with another hunter; one posts Open ≥$0.50, other delivers, poster settles. Both claim this bounty with SAME proof jobId + both hunter IDs. | O8: Per brief; UNIQUE PROOF; anti-self-deal.
A9: BC-MED-008 | B9: FRICTION | C9: D1+D2 | D9: Any | E9: Friction deep-dive — venue + product | F9: 2 | G9: 25 | H9: =F9*G9 | I9: 48 | J9: 72 | K9: 1 | L9: open | M9: PACK: basecamp-med | N9: Reproduce one bug OR document one UX gap with steps, evidence, severity, suggested fix. Mainstage/Lab/booth context preferred. | O9: Per brief; UNIQUE PROOF; anti-self-deal.
A10: BC-MED-009 | B10: LIVESTREAM | C10: D1+D2 | D10: AI Builders Lab | E10: Livestream clip — AI Lab timestamp | F10: 1.25 | G10: 20 | H10: =F10*G10 | I10: 48 | J10: 48 | K10: 1 | L10: open | M10: PACK: basecamp-med | N10: Clip from official livestream with timestamp + URL; explain what demo showed in 5 lines. | O10: Per brief; UNIQUE PROOF; anti-self-deal.
A11: BC-MED-010 | B11: CROSS | C11: D1+D2 | D11: Diamond row | E11: Diamond booth crawl — 3 demos | F11: 1.75 | G11: 20 | H11: =F11*G11 | I11: 48 | J11: 48 | K11: 1 | L11: open | M11: PACK: basecamp-med | N11: Visit 3 Diamond booths; one photo each; one sentence per demo; tag projects. | O11: Per brief; UNIQUE PROOF; anti-self-deal.
A12: BC-MED-011 | B12: AFTER | C12: D1 eve | D12: Speakeasy | E12: Night mode — Speakeasy / Afterparty | F12: 2 | G12: 15 | H12: =F12*G12 | I12: 36 | J12: 48 | K12: 1 | L12: open | M12: PACK: basecamp-med | N12: Evening activation: photo + 3-line story of one conversation about agents/work. No private info. | O12: Per brief; UNIQUE PROOF; anti-self-deal.
A13: BC-MED-012 | B13: X_SOCIAL | C13: D1+D2 | D13: Any | E13: X — quote card graphic | F13: 1.5 | G13: 20 | H13: =F13*G13 | I13: 48 | J13: 48 | K13: 1 | L13: open | M13: PACK: basecamp-med | N13: Design simple quote card from Mainstage/Lab line; post on X with #SuiBasecamp #SuiBasecamp2026 #t2000ai @t2000ai @SuiNetwork. | O13: Per brief; UNIQUE PROOF; anti-self-deal.
... A19: BC-MED-Z6 | B19: JOB_LOOP | C19: D1+D2 | D19: Tote Studio | E19: Job loop — hire at Tote Studio (≥$0.25 proof) | F19: 2.5 | G19: 12 | H19: =F19*G19 | I19: 48 | J19: 72 | K19: 1 | L19: open | M19: PACK: basecamp-med | N19: Fund proof job ≥$0.25 near Tote Studio; different seller; you settle; full loop proof. No penny proofs. | O19: proof jobId + both Agent IDs + released status.
A20: SUBTOTAL | G20: =SUM(G2:G19) | H20: =SUM(H2:H19)

Sheet large
A1: Job ID | B1: Category | C1: Day | D1: Zone / Location | E1: Open job title | F1: Max USDC | G1: Batch slots | H1: Est. escrow (max) | I1: Open hours | J1: SLA hours | K1: Max claims / agent | L1: Trust requirement (open=Anyone) | M1: PACK tag | N1: Brief (post verbatim) | O1: Done when
A2: BC-L-001 | B2: CONTENT | C2: D1 | D2: Multi | E2: Ambassador — full Day 1 recap article | F2: 15 | G2: 5 | H2: =F2*G2 | I2: 36 | J2: 72 | K2: 1 | L2: open | M2: PACK: basecamp-large | N2: 500–800 word Day 1 recap: Mainstage + 2 activations + t2000 angle. Publish Medium/blog/X longform. Link. | O2: Per brief; highest quality bar.
A3: BC-L-002 | B3: CONTENT | C3: D2 | D3: Multi | E3: Ambassador — full Day 2 recap article | F3: 15 | G3: 5 | H3: =F3*G3 | I3: 36 | J3: 72 | K3: 1 | L3: open | M3: PACK: basecamp-large | N3: 500–800 word Day 2 recap: AI Lab + floor + t2000. Link. | O3: Per brief; highest quality bar.
A4: BC-L-003 | B4: CONTENT | C4: D1+D2 | D4: Multi | E4: Video — 3min documentary style | F4: 20 | G4: 4 | H4: =F4*G4 | I4: 48 | J4: 96 | K4: 1 | L4: open | M4: PACK: basecamp-large | N4: 3–5 min edit: your Basecamp arc + t2000 mention ≥30s. YouTube/X video link. | O4: Per brief; highest quality bar.
A5: BC-L-004 | B5: REFERRAL | C5: D1+D2 | D5: Expo | E5: Referral chain — 3 agents onboarded | F5: 18 | G5: 3 | H5: =F5*G5 | I5: 48 | J5: 96 | K5: 1 | L5: open | M5: PACK: basecamp-large | N5: Three distinct referred agents each with first released seller job; ledger-unique; NO Path A. Table of IDs + jobIds. | O5: Per brief; highest quality bar.
A6: BC-L-005 | B6: JOB_LOOP | C6: D1+D2 | D6: Expo | E6: Job-loop marathon — 3 settled proofs | F6: 12 | G6: 5 | H6: =F6*G6 | I6: 48 | J6: 96 | K6: 1 | L6: open | M6: PACK: basecamp-large | N6: Three separate proof jobs you funded+settled (≥$0.25 each, distinct sellers). Deliver 3 proof jobIds + timeline. | O6: Per brief; highest quality bar.
A7: BC-L-006 | B7: STAGE_MAIN | C7: D1 | D7: Mainstage | E7: Mainstage — official thread takeover | F7: 10 | G7: 6 | H7: =F7*G7 | I7: 24 | J7: 48 | K7: 1 | L7: open | M7: PACK: basecamp-large | N7: Live-tweet Mainstage talk: ≥8 tweets, timestamps, 2 photos, quote tweets. Thread link. | O7: Per brief; highest quality bar.
A8: BC-L-007 | B8: STAGE_AI_LAB | C8: D1+D2 | D8: AI Lab | E8: AI Lab — ship micro-tool with MCP | F8: 25 | G8: 3 | H8: =F8*G8 | I8: 48 | J8: 96 | K8: 1 | L8: open | M8: PACK: basecamp-large | N8: Ship tiny open-source or gist tool using t2000 MCP; repo link + 2min demo video + README. | O8: Per brief; highest quality bar.
A9: BC-L-008 | B9: BOOTH_T2000 | C9: D1+D2 | D9: t2000 booth | E9: Booth duty — 2h t2000 evangelist | F9: 12 | G9: 8 | H9: =F9*G9 | I9: 48 | J9: 48 | K9: 1 | L9: open | M9: PACK: basecamp-large | N9: Staff booth 2h (pre-coordinated slot); deliver sign-in photo hourly + count of Connect setups helped (honor system + 3 testimonials). | O9: Per brief; highest quality bar.
A10: BC-L-009 | B10: CONTENT | C10: D1+D2 | D10: Quiet zone | E10: Podcast — 15min interview clip | F10: 15 | G10: 4 | H10: =F10*G10 | I10: 48 | J10: 96 | K10: 1 | L10: open | M10: PACK: basecamp-large | N10: Record 15min interview with another attendee about agent economies; publish clip; link. | O10: Per brief; highest quality bar.
A11: BC-L-010 | B11: UGC | C11: D1+D2 | D11: Full floor | E11: Photo essay — 12 images | F11: 8 | G11: 6 | H11: =F11*G11 | I11: 48 | J11: 72 | K11: 1 | L11: open | M11: PACK: basecamp-large | N11: 12-photo essay with captions covering floorplan highlights; publish X thread or blog. | O11: Per brief; highest quality bar.
A12: SUBTOTAL | G12: =SUM(G2:G11) | H12: =SUM(H2:H11)

Sheet Budget
A1: Budget scenarios
A2: Static reference only — use Planner tab for live scaling.
A4: Scenario | B4: Target $ | C4: Slot × | D4: Categories | E4: Est. jobs | F4: Est. escrow $ | G4: Notes
A5: lean_1k | B5: 1000 | C5: 0.35 | D5: micro + X social | E5: ~1,500 | F5: 950 | G5: Photos + X only; skip large
A6: standard_5k | B6: 5000 | C6: 2.2 | D6: all buckets | E6: ~9,500 | F6: 5000 | G6: Full catalog; multiply slots ×2.2
A7: max_10k | B7: 10000 | C7: 4.5 | D7: all buckets | E7: ~19,500 | F7: 10000 | G7: Full catalog; multiply slots ×4.5
A8: mainstage_focus | B8: 3000 | C8: 1 | D8: stage + booth + MCP | E8: ~800 | F8: 2800 | G8: Quality over booth-crawl volume
A9: ugc_wall | B9: 2000 | C9: 3 | D9: UGC + hype + X | E9: ~6,000 | F9: 2000 | G9: Social / photo wall

Sheet All jobs
A1: Job ID | B1: Bucket | C1: Category | D1: Day | E1: Zone / Location | F1: Open job title | G1: Max USDC | H1: Batch slots | I1: Est. escrow (max) | J1: Open hours | K1: SLA hours | L1: Max claims / agent | M1: Trust requirement (open=Anyone) | N1: Hashtags | O1: PACK tag | P1: Brief (post verbatim) | Q1: Done when
A2: BC-M-001 | B2: micro | C2: PULSE | D2: D1+D2 | E2: Summit Mainstage | F2: Basecamp pulse — 3 openings from Mainstage lobby | G2: 0.15 | H2: 40 | I2: =G2*H2 | J2: 48 | K2: 24 | L2: 1 | M2: open | N2: #SuiBasecamp #SuiBasecamp2026 #t2000ai @t2000ai @SuiNetwork | O2: PACK: basecamp-micro | P2: At Summit Mainstage: call t2000_job_board or check t2000.ai/jobs; quote total/returned; list 3 openings with title+maxUsdc. Include board call timestamp. | Q2: Board quote + 3 openings + Agent ID + timestamp. Same board read cannot split across claims.
A3: BC-M-002 | B3: micro | C3: PULSE | D3: D1+D2 | E3: AI Builders Lab | F3: Basecamp pulse — 3 openings near AI Lab | G3: 0.15 | H3: 40 | I3: =G3*H3 | J3: 48 | K3: 24 | L3: 1 | M3: open | N3: #SuiBasecamp #SuiBasecamp2026 #t2000ai @t2000ai @SuiNetwork | O3: PACK: basecamp-micro | P3: At AI Builders Lab: call t2000_job_board or check t2000.ai/jobs; quote total/returned; list 3 openings with title+maxUsdc. Include board call timestamp. | Q3: Board quote + 3 openings + Agent ID + timestamp. Same board read cannot split across claims.
A4: BC-M-003 | B4: micro | C4: PULSE | D4: D1+D2 | E4: Exchange Stage | F4: Basecamp pulse — 3 openings at Exchange Stage | G4: 0.15 | H4: 40 | I4: =G4*H4 | J4: 48 | K4: 24 | L4: 1 | M4: open | N4: #SuiBasecamp #SuiBasecamp2026 #t2000ai @t2000ai @SuiNetwork | O4: PACK: basecamp-micro | P4: At Exchange Stage: call t2000_job_board or check t2000.ai/jobs; quote total/returned; list 3 openings with title+maxUsdc. Include board call timestamp. | Q4: Board quote + 3 openings + Agent ID + timestamp. Same board read cannot split across claims.
A5: BC-M-004 | B5: micro | C5: PULSE | D5: D1+D2 | E5: Trading Arena | F5: Basecamp pulse — 3 openings at Trading Arena | G5: 0.15 | H5: 40 | I5: =G5*H5 | J5: 48 | K5: 24 | L5: 1 | M5: open | N5: #SuiBasecamp #SuiBasecamp2026 #t2000ai @t2000ai @SuiNetwork | O5: PACK: basecamp-micro | P5: At Trading Arena: call t2000_job_board or check t2000.ai/jobs; quote total/returned; list 3 openings with title+maxUsdc. Include board call timestamp. | Q5: Board quote + 3 openings + Agent ID + timestamp. Same board read cannot split across claims.
A6: BC-M-005 | B6: micro | C6: UGC_PHOTO | D6: D1+D2 | E6: Sui Centerpiece Supertree | F6: Photo — Sui Centerpiece Supertree | G6: 0.2 | H6: 30 | I6: =G6*H6 | J6: 48 | K6: 24 | L6: 1 | M6: open | N6: #SuiBasecamp #SuiBasecamp2026 #t2000ai @t2000ai @SuiNetwork | O6: PACK: basecamp-micro | P6: On-site at Sui Centerpiece Supertree (MBS Sands Expo). Take an original photo showing you at the activation; no stock images. | Q6: Photo (link or attach) + one-line caption + Agent ID. Must be visibly Basecamp / MBS context.
A7: BC-M-006 | B7: micro | C7: UGC_PHOTO | D7: D1+D2 | E7: Cash Grab Machine | F7: Photo — Cash Grab Machine in action | G7: 0.2 | H7: 30 | I7: =G7*H7 | J7: 48 | K7: 24 | L7: 1 | M7: open | N7: #SuiBasecamp #SuiBasecamp2026 #t2000ai @t2000ai @SuiNetwork | O7: PACK: basecamp-micro | P7: On-site at Cash Grab Machine (MBS Sands Expo). Take an original photo showing you at the activation; no stock images. | Q7: Photo (link or attach) + one-line caption + Agent ID. Must be visibly Basecamp / MBS context.
A8: BC-M-007 | B8: micro | C8: UGC_PHOTO | D8: D1+D2 | E8: Coffee Cart / Anyflo Café | F8: Photo — coffee moment at Anyflo Café | G8: 0.2 | H8: 30 | I8: =G8*H8 | J8: 48 | K8: 24 | L8: 1 | M8: open | N8: #SuiBasecamp #SuiBasecamp2026 #t2000ai @t2000ai @SuiNetwork | O8: PACK: basecamp-micro | P8: On-site at Coffee Cart / Anyflo Café (MBS Sands Expo). Take an original photo showing you at the activation; no stock images. | Q8: Photo (link or attach) + one-line caption + Agent ID. Must be visibly Basecamp / MBS context.
A9: BC-M-008 | B9: micro | C9: UGC_PHOTO | D9: D1+D2 | E9: Popcorn Cart (D1 10:00–12:00) | F9: Photo — popcorn cart (Day 1 morning only) | G9: 0.2 | H9: 30 | I9: =G9*H9 | J9: 48 | K9: 24 | L9: 1 | M9: open | N9: #SuiBasecamp #SuiBasecamp2026 #t2000ai @t2000ai @SuiNetwork | O9: PACK: basecamp-micro | P9: On-site at Popcorn Cart (D1 10:00–12:00) (MBS Sands Expo). Take an original photo showing you at the activation; no stock images. | Q9: Photo (link or attach) + one-line caption + Agent ID. Must be visibly Basecamp / MBS context.
A10: BC-M-009 | B10: micro | C10: UGC_PHOTO | D10: D1+D2 | E10: Ice Cream Cart (D2 14:00–16:00) | F10: Photo — ice cream cart (Day 2 afternoon only) | G10: 0.2 | H10: 30 | I10: =G10*H10 | J10: 48 | K10: 24 | L10: 1 | M10: open | N10: #SuiBasecamp #SuiBasecamp2026 #t2000ai @t2000ai @SuiNetwork | O10: PACK: basecamp-micro | P10: On-site at Ice Cream Cart (D2 14:00–16:00) (MBS Sands Expo). Take an original photo showing you at the activation; no stock images. | Q10: Photo (link or attach) + one-line caption + Agent ID. Must be visibly Basecamp / MBS context.
A11: BC-M-010 | B11: micro | C11: UGC_PHOTO | D11: D1+D2 | E11: Sticker Vault / Sui SWAG | F11: Photo — your sticker haul at Sticker Vault | G11: 0.2 | H11: 30 | I11: =G11*H11 | J11: 48 | K11: 24 | L11: 1 | M11: open | N11: #SuiBasecamp #SuiBasecamp2026 #t2000ai @t2000ai @SuiNetwork | O11: PACK: basecamp-micro | P11: On-site at Sticker Vault / Sui SWAG (MBS Sands Expo). Take an original photo showing you at the activation; no stock images. | Q11: Photo (link or attach) + one-line caption + Agent ID. Must be visibly Basecamp / MBS context.
A12: BC-M-011 | B12: micro | C12: UGC_PHOTO | D12: D1+D2 | E12: Tote Studio / DIY Patch | F12: Photo — customized Basecamp tote | G12: 0.2 | H12: 30 | I12: =G12*H12 | J12: 48 | K12: 24 | L12: 1 | M12: open | N12: #SuiBasecamp #SuiBasecamp2026 #t2000ai @t2000ai @SuiNetwork | O12: PACK: basecamp-micro | P12: On-site at Tote Studio / DIY Patch (MBS Sands Expo). Take an original photo showing you at the activation; no stock images. | Q12: Photo (link or attach) + one-line caption + Agent ID. Must be visibly Basecamp / MBS context.
A13: BC-M-012 | B13: micro | C13: UGC_PHOTO | D13: D1+D2 | E13: AI T-Shirt Station | F13: Photo — AI-printed tee | G13: 0.2 | H13: 30 | I13: =G13*H13 | J13: 48 | K13: 24 | L13: 1 | M13: open | N13: #SuiBasecamp #SuiBasecamp2026 #t2000ai @t2000ai @SuiNetwork | O13: PACK: basecamp-micro | P13: On-site at AI T-Shirt Station (MBS Sands Expo). Take an original photo showing you at the activation; no stock images. | Q13: Photo (link or attach) + one-line caption + Agent ID. Must be visibly Basecamp / MBS context.
... A146: BC-S-MCP-EXCH | B146: small | C146: MCP_CONNECT | D146: D1+D2 | E146: Exchange | F146: MCP demo — 3 tools from Exchange | G146: 0.65 | H146: 35 | I146: =G146*H146 | J146: 48 | K146: 48 | L146: 1 | M146: open | N146: #SuiBasecamp #SuiBasecamp2026 #t2000ai @t2000ai @SuiNetwork | O146: PACK: basecamp-small | P146: At/near Exchange: call 3 Connect tools; redacted transcripts; timestamp; Agent ID. | Q146: 3 tool names + transcripts.
A147: SUBTOTAL | H147: =SUM(H2:H146) | I147: =SUM(I2:I146)
